reykit/__init__.py
reykit/rall.py
reykit/rbase.py
reykit/rdata.py
reykit/remail.py
reykit/rimage.py
reykit/rlog.py
reykit/rmonkey.py
reykit/rnet.py
reykit/rnum.py
reykit/ros.py
reykit/rrand.py
reykit/rre.py
reykit/rschedule.py
reykit/rstdout.py
reykit/rsys.py
reykit/rtable.py
reykit/rtask.py
reykit/rtext.py
reykit/rtime.py
reykit/rwrap.py
reykit/rdll/__init__.py
reykit/rdll/rdll_core.py
reykit-1.2.36.dist-info/METADATA
reykit-1.2.36.dist-info/WHEEL
reykit-1.2.36.dist-info/licenses/LICENSE
reykit-1.2.36.dist-info/RECORD
