Metadata-Version: 2.4
Name: reykit
Version: 1.2.36
Summary: Kit method set.
Project-URL: homepage, https://github.com/reyxbo/reykit/
Author-email: Rey <reyxbo@163.com>
License: Copyright 2025 ReyXBo
License-File: LICENSE
Keywords: kit,rey,reyxbo,tool
Requires-Python: >=3.12
Requires-Dist: aiohttp
Requires-Dist: apscheduler
Requires-Dist: bcrypt
Requires-Dist: captcha
Requires-Dist: concurrent-log-handler
Requires-Dist: filetype
Requires-Dist: pandas
Requires-Dist: pdfplumber
Requires-Dist: pillow
Requires-Dist: psutil
Requires-Dist: pyjwt
Requires-Dist: pymem
Requires-Dist: python-docx
Requires-Dist: pyzbar
Requires-Dist: qrcode
Requires-Dist: requests
Requires-Dist: requests-cache
Requires-Dist: reydb
Requires-Dist: varname
